Metadata-Version: 2.4
Name: scanpy_workflow_support_functions
Version: 0.1.3
Summary: This package has the compilations of functions useful for the scanpy guided single cell RNAseq analysis
Author-email: Ankit Patel <ankit.patel@qmul.ac.uk>
Project-URL: Homepage, https://github.com/avpatel18/scanpy_workflow_support_functions
Project-URL: Bug Tracker, https://github.com/avpatel18/scanpy_workflow_support_functions/issues
Requires-Python: >=3.10
License-File: LICENCE
Requires-Dist: numpy
Requires-Dist: pandas
Requires-Dist: scanpy
Requires-Dist: squidpy
Requires-Dist: cell2location
Dynamic: license-file
